Metadata-Version: 2.1
Name: example-pkg-bigabig
Version: 0.0.1
Summary: A small example package
Home-page: https://github.com/bigabig/packaging_tutorial
Author: Tim Fischer
Author-email: tim.s.fischer96@googlemail.com
License: UNKNOWN
Project-URL: Bug Tracker, https://github.com/bigabig/packaging_tutorial/issues
Platform: UNKNOWN
Classifier: Programming Language :: Python :: 3
Classifier: License :: OSI Approved :: Apache Software License
Classifier: Operating System :: OS Independent
Requires-Python: >=3.6
License-File: LICENSE
Requires-Dist: numpy
